[
  {
    "movie_name": "Parasite",
    "imdb_ratings": 8.6,
    "year": "(2019)",
    "overview": "Greed and class discrimination threaten the newly formed symbiotic relationship between the wealthy Park family and the destitute Kim clan.",
    "Parental_guidance": "R",
    "length": "132 min",
    "movie_id": "48311",
    "metascore": 97,
    "genre": "Comedy, Drama, Thriller",
    "director": "Bong Joon Ho",
    "actor1": "Kang-ho Song",
    "actor2": "Lee Sun-kyun",
    "actor3": "Cho Yeo-jeong",
    "actor4": "Choi Woo-sik",
    "poster": "https://upload.wikimedia.org/wikipedia/en/5/53/Parasite_%282019_film%29.png"
  },
  {
    "movie_name": "Life Is Beautiful",
    "imdb_ratings": 8.6,
    "year": "(1997)",
    "metascore": 94,
    "movie_id": "242593",
    "overview": "When an open-minded Jewish librarian and his son become victims of the Holocaust, he uses a perfect mixture of will, humor, and imagination to protect his son from the dangers around their camp.",
    "Parental_guidance": "PG-13",
    "length": "116 min",
    "genre": "Comedy, Drama, Romance",
    "director": "Roberto Benigni",
    "actor1": "Roberto Benigni",
    "actor2": "Nicoletta Braschi",
    "poster": "https://upload.wikimedia.org/wikipedia/en/7/7c/Vitaebella.jpg",
    "actor3": "Giorgio Cantarini",
    "actor4": "Giustino Durano"
  },
  {
    "movie_name": "The Intouchables",
    "metascore": 93,
    "imdb_ratings": 8.5,
    "movie_id": "77338",
    "year": "(2011)",
    "overview": "After he becomes a quadriplegic from a paragliding accident, an aristocrat hires a young man from the projects to be his caregiver.",
    "Parental_guidance": "R",
    "length": "112 min",
    "genre": "Biography, Comedy, Drama",
    "director": "Olivier Nakache",
    "actor1": "Éric Toledano",
    "poster": "https://upload.wikimedia.org/wikipedia/en/9/93/The_Intouchables.jpg",
    "actor2": "François Cluzet",
    "actor3": "Omar Sy",
    "actor4": "Anne Le Ny"
  },
  {
    "movie_name": "Back to the Future",
    "imdb_ratings": 8.5,
    "metascore": 91,
    "movie_id": "105",
    "year": "(1985)",
    "overview": "Marty McFly, a 17-year-old high school student, is accidentally sent thirty years into the past in a time-traveling DeLorean invented by his close friend, the eccentric scientist Doc Brown.",
    "Parental_guidance": "PG",
    "length": "116 min",
    "genre": "Adventure, Comedy, Sci-Fi",
    "director": "Robert Zemeckis",
    "actor1": "Michael J. Fox",
    "poster": "https://upload.wikimedia.org/wikipedia/en/d/d2/Back_to_the_Future.jpg",
    "actor2": "Christopher Lloyd",
    "actor3": "Lea Thompson",
    "actor4": "Crispin Glover"
  },
  {
    "movie_name": "Modern Times",
    "imdb_ratings": 8.5,
    "year": "(1936)",
    "metascore": 97,
    "movie_id": "3082",
    "overview": "The Tramp struggles to live in modern industrial society with the help of a young homeless woman.",
    "Parental_guidance": "G",
    "length": "87 min",
    "genre": "Comedy, Drama, Family",
    "director": "Charles Chaplin",
    "poster": "https://upload.wikimedia.org/wikipedia/commons/3/36/Modern_Times_poster.jpg",
    "actor1": "Charles Chaplin",
    "actor2": "Paulette Goddard",
    "actor3": "Henry Bergman",
    "actor4": "Tiny Sandford"
  },
  {
    "movie_name": "City Lights",
    "imdb_ratings": 8.5,
    "metascore": 89,
    "year": "(1931)",
    "movie_id": "901",
    "overview": "With the aid of a wealthy erratic tippler, a dewy-eyed tramp who has fallen in love with a sightless flower girl accumulates money to be able to help her medically.",
    "Parental_guidance": "G",
    "length": "87 min",
    "genre": "Comedy, Drama, Romance",
    "director": "Charles Chaplin",
    "actor1": "Charles Chaplin",
    "actor2": "Virginia Cherrill",
    "actor3": "Florence Lee",
    "poster": "https://upload.wikimedia.org/wikipedia/commons/0/09/City_Lights_%281931_theatrical_poster_-_retouched%29.jpg",
    "actor4": "Harry Myers"
  },
  {
    "movie_name": "3 Idiots",
      "metascore":87, 
    "imdb_ratings": 8.4,
    "year": "(2009)",
    "movie_id": "20453",
    "overview": "Two friends are searching for their long lost companion. They revisit their college days and recall the memories of their friend who inspired them to think differently, even as the rest of the world called them \"idiots\".",
    "Parental_guidance": "PG-13",
    "length": "170 min",
    "genre": "Comedy, Drama",
    "director": "Rajkumar Hirani",
    "actor1": "Aamir Khan",
    "actor2": "Madhavan",
    "actor3": "Mona Singh",
    "poster": "https://upload.wikimedia.org/wikipedia/en/d/df/3_idiots_poster.jpg",
    "actor4": "Sharman Joshi"
  },
  {
    "movie_name": "Dr. Strangelove or: How I Learned to Stop Worrying and Love the Bomb",
    "imdb_ratings": 8.4,
    "movie_id": "935",
      "metascore": 87,
    "year": "(1964)",
    "overview": "An insane general triggers a path to nuclear holocaust that a War Room full of politicians and generals frantically tries to stop.",
    "Parental_guidance": "PG",
    "length": "95 min",
    "genre": "Comedy",
    "director": "Stanley Kubrick",
    "actor1": "Peter Sellers",
    "actor2": "George C. Scott",
    "poster": "https://upload.wikimedia.org/wikipedia/en/e/e6/Dr._Strangelove_poster.jpg",
    "actor3": "Sterling Hayden",
    "actor4": "Keenan Wynn"
  },
  {
    "movie_name": "The Great Dictator",
    "imdb_ratings": 8.4,
      "metascore": 85,
    "year": "(1940)",
    "movie_id": "914",
    "overview": "Dictator Adenoid Hynkel tries to expand his empire while a poor Jewish barber tries to avoid persecution from Hynkel's regime.",
    "Parental_guidance": "Passed",
    "length": "125 min",
    "genre": "Comedy, Drama, War",
    "director": "Charles Chaplin",
    "actor1": "Charles Chaplin",
    "actor2": "Paulette Goddard",
    "poster": "https://upload.wikimedia.org/wikipedia/commons/9/9d/The_Great_Dictator_%281940%29_poster.jpg",
    "actor3": "Jack Oakie",
    "actor4": "Reginald Gardiner"
  },
  {
    "movie_name": "Amélie",
    "imdb_ratings": 8.3,
    "year": "(2001)",
    "overview": "Amélie is an innocent and naive girl in Paris with her own sense of justice. She decides to help those around her and, along the way, discovers love.",
    "Parental_guidance": "R",
      "metascore": 82,
    "length": "122 min",
    "movie_id": "194",
    "genre": "Comedy, Romance",
    "director": "Jean-Pierre Jeunet",
    "poster": "https://upload.wikimedia.org/wikipedia/en/5/53/Amelie_poster.jpg",
    "actor1": "Audrey Tautou",
    "actor2": "Mathieu Kassovitz",
    "actor3": "Rufus",
    "actor4": "Lorella Cravotta"
  },
  {
    "movie_name": "Snatch",
    "imdb_ratings": 8.3,
      "metascore": 81,
    "year": "(2000)",
    "overview": "Unscrupulous boxing promoters, violent bookmakers, a Russian gangster, incompetent amateur robbers and supposedly Jewish jewelers fight to track down a priceless stolen diamond.",
    "Parental_guidance": "R",
    "length": "102 min",
    "genre": "Comedy, Crime",
    "director": "Guy Ritchie",
    "movie_id": "107",
    "poster": "https://static.wikia.nocookie.net/snatch/images/1/1a/Snatch_Film_Poster.jpg/revision/latest?cb=20170314175733",
    "actor1": "Jason Statham",
    "actor2": "Brad Pitt",
    "actor3": "Benicio Del Toro",
    "actor4": "Dennis Farina"
  },
  {
    "movie_name": "Toy Story",
    "imdb_ratings": 8.3,
    "movie_id": "862",
      "metascore":83,
    "year": "(1995)",
    "overview": "A cowboy doll is profoundly threatened and jealous when a new spaceman figure supplants him as top toy in a boy's room.",
    "Parental_guidance": "G",
    "length": "81 min",
    "genre": "Animation, Adventure, Comedy",
    "director": "John Lasseter",
    "actor1": "Tom Hanks",
    "poster": "https://upload.wikimedia.org/wikipedia/en/1/13/Toy_Story.jpg",
    "actor2": "Tim Allen",
    "actor3": "Don Rickles",
    "actor4": "Jim Varney"
  },
  {
    "movie_name": "The Sting",
    "imdb_ratings": 8.3,
    "movie_id": "9277",
    "year": "(1973)",
      "metascore": 86,
    "overview": "Two grifters team up to pull off the ultimate con.",
    "Parental_guidance": "PG",
    "length": "129 min",
    "genre": "Comedy, Crime, Drama",
    "director": "George Roy Hill",
    "actor1": "Paul Newman",
    "poster": "https://upload.wikimedia.org/wikipedia/commons/a/aa/The_Sting_%281973_alt_poster%29.jpeg",
    "actor2": "Robert Redford",
    "actor3": "Robert Shaw",
    "actor4": "Charles Durning"
  },
  {
    "movie_name": "The Apartment",
    "imdb_ratings": 8.3,
    "year": "(1960)",
      "metascore": 80,
    "movie_id": "284",
    "overview": "A man tries to rise in his company by letting its executives use his apartment for trysts, but complications and a romance of his own ensue.",
    "Parental_guidance": "Approved",
    "length": "125 min",
    "genre": "Comedy, Drama, Romance",
    "director": "Billy Wilder",
    "actor1": "Jack Lemmon",
    "actor2": "Shirley MacLaine",
    "poster": "https://upload.wikimedia.org/wikipedia/commons/8/8b/The_Apartment_%281960_poster%29.jpg",
    "actor3": "Fred MacMurray",
    "actor4": "Ray Walston"
  },
  {
    "movie_name": "Singin' in the Rain",
    "imdb_ratings": 8.3,
    "movie_id": "872",
    "year": "(1952)",
      "metascore": 81,
    "overview": "A silent film production company and cast make a difficult transition to sound.",
    "Parental_guidance": "G",
    "length": "103 min",
    "genre": "Comedy, Musical, Romance",
    "director": "Stanley Donen",
    "actor1": "Gene Kelly",
    "actor2": "Gene Kelly",
    "actor3": "Donald O'Connor",
    "poster": "https://upload.wikimedia.org/wikipedia/commons/5/5d/Singin%27_in_the_Rain_%281952_poster%29.jpg",
    "actor4": "Debbie Reynolds"
  },
  {
    "movie_name": "The Kid",
    "movie_id": "492565",
      "metascore": 87,
    "imdb_ratings": 8.3,
    "year": "(1921)",
    "overview": "The Tramp cares for an abandoned child, but events put that relationship in jeopardy.",
    "Parental_guidance": "Passed",
    "length": "68 min",
    "genre": "Comedy, Drama, Family",
    "director": "Charles Chaplin",
    "actor1": "Charles Chaplin",
    "poster": "https://upload.wikimedia.org/wikipedia/commons/5/59/CC_The_Kid_1921.jpg",
    "actor2": "Edna Purviance",
    "actor3": "Jackie Coogan",
    "actor4": "Carl Miller"
  },
  {
    "movie_name": "Chhichhore",
    "imdb_ratings": 8.2,
    "movie_id": "596650",
    "year": "(2019)",
      "metascore": 80,
    "overview": "A tragic incident forces Anirudh, a middle-aged man, to take a trip down memory lane and reminisce his college days along with his friends, who were labelled as losers.",
    "Parental_guidance": "Not Rated",
    "length": "143 min",
    "genre": "Comedy, Drama",
    "poster": "https://upload.wikimedia.org/wikipedia/en/3/3d/Chhichhore_Poster.jpg",
    "director": "Nitesh Tiwari",
    "actor1": "Sushant Singh Rajput",
    "actor2": "Shraddha Kapoor",
    "actor3": "Varun Sharma",
    "actor4": "Prateik"
  },
  {
    "movie_name": "Green Book",
    "imdb_ratings": 8.2,
    "movie_id": "490132",
      "metascore": 79,
    "year": "(2018)",
    "overview": "A working-class Italian-American bouncer becomes the driver of an African-American classical pianist on a tour of venues through the 1960s American South.",
    "Parental_guidance": "PG-13",
    "length": "130 min",
    "genre": "Biography, Comedy, Drama",
    "director": "Peter Farrelly",
    "poster": "https://upload.wikimedia.org/wikipedia/en/5/5b/Green_Book_%282018_poster%29.png",
    "actor1": "Viggo Mortensen",
    "actor2": "Mahershala Ali",
    "actor3": "Linda Cardellini",
    "actor4": "Sebastian Maniscalco"
  },
  {
    "movie_name": "Three Billboards Outside Ebbing, Missouri",
    "imdb_ratings": 8.2,
    "year": "(2017)",
    "movie_id": "359940",
      "metascore": 78,
      "poster": "https://upload.wikimedia.org/wikipedia/en/c/c7/Three_Billboards_Outside_Ebbing%2C_Missouri_poster.png",
    "overview": "A mother personally challenges the local authorities to solve her daughter's murder when they fail to catch the culprit.",
    "Parental_guidance": "R",
    "length": "115 min",
    "genre": "Comedy, Crime, Drama",
    "director": "Martin McDonagh",
    "actor1": "Frances McDormand",
    "actor2": "Woody Harrelson",
    "actor3": "Sam Rockwell",
    "actor4": "Caleb Landry Jones"
  },
  {
    "movie_name": "Klaus",
    "imdb_ratings": 8.2,
    "movie_id": "508965",
    "year": "(2019)",
    "metascore": 77,
    "overview": "A simple act of kindness always sparks another, even in a frozen, faraway place. When Smeerensburg's new postman, Jesper, befriends toymaker Klaus, their gifts melt an age-old feud and deliver a sleigh full of holiday traditions.",
    "Parental_guidance": "PG",
    "poster": "https://upload.wikimedia.org/wikipedia/en/2/26/Klaus_poster.jpeg",
    "length": "96 min",
    "genre": "Animation, Adventure, Comedy",
    "director": "Sergio Pablos",
    "actor1": "Carlos Martínez López",
    "actor2": "Jason Schwartzman",
    "actor3": "J.K. Simmons",
    "actor4": "Rashida Jones"
  }

]